LICENSE.txt
MANIFEST.in
README.md
setup.cfg
setup.py
iamgif/__init__.py
iamgif/iamgif.py
iamgif.egg-info/PKG-INFO
iamgif.egg-info/SOURCES.txt
iamgif.egg-info/dependency_links.txt
iamgif.egg-info/requires.txt
iamgif.egg-info/top_level.txt