Metadata-Version: 1.1
Name: iamgif
Version: 0.0.1
Summary: Python library to convert text to GIF
Home-page: https://github.com/rahulxxarora/iamgif
Author: Rahul Arora
Author-email: coderahul94@gmail.com
License: MIT
Keywords: GIF PYthon text to image
Platform: UNKNOWN
Classifier: Intended Audience :: Developers
Classifier: License :: OSI Approved :: MIT License
Classifier: Programming Language :: Python
Classifier: Operating System :: POSIX
